{"cameraMode":{"drawMode":0,"name":"Shaded","section":"Shading Mode"},"sceneLighting":false,"audioPlay":false,"sceneViewState":{"m_AlwaysRefresh":false,"showFog":true,"showSkybox":false,"showFlares":true,"showImageEffects":true,"showParticleSystems":true,"showVisualEffectGraphs":true,"m_FxEnabled":true},"in2DMode":false,"pivot":{"x":1.332855224609375,"y":18.113075256347658,"z":0.4480743408203125},"rotation":{"x":-0.2578209638595581,"y":0.6159754991531372,"z":-0.22366124391555787,"w":-0.7100080847740173},"size":312.0812072753906,"orthographic":false}